CMLv1/__init__.py
CMLv1/base.py
CMLv1/error.py
CMLv1-0.1.1.dist-info/METADATA
CMLv1-0.1.1.dist-info/WHEEL
CMLv1-0.1.1.dist-info/top_level.txt
CMLv1-0.1.1.dist-info/RECORD
